alumathpeergroup10/__init__.py
alumathpeergroup10/matrix.py
alumathpeergroup10/operations.py
tests/__init__.py
tests/test_matrix.py
alumathpeergroup10-0.1.0.dist-info/METADATA
alumathpeergroup10-0.1.0.dist-info/WHEEL
alumathpeergroup10-0.1.0.dist-info/top_level.txt
alumathpeergroup10-0.1.0.dist-info/RECORD
